Metadata-Version: 2.1
Name: odoo13-addon-account-fiscal-position-rule
Version: 13.0.1.3.1
Summary: Account Fiscal Position Rule
Home-page: https://github.com/OCA/account-fiscal-rule
Author: Akretion, Odoo Community Association (OCA)
Author-email: support@odoo-community.org
License: AGPL-3
Platform: UNKNOWN
Classifier: Programming Language :: Python
Classifier: Framework :: Odoo
Classifier: Framework :: Odoo :: 13.0
Classifier: License :: OSI Approved :: GNU Affero General Public License v3
Requires-Python: >=3.5
Requires-Dist: odoo (<13.1dev,>=13.0a)
